terminy/__init__.py
terminy-0.0.1.dist-info/LICENSE
terminy-0.0.1.dist-info/METADATA
terminy-0.0.1.dist-info/WHEEL
terminy-0.0.1.dist-info/top_level.txt
terminy-0.0.1.dist-info/RECORD
